factorio_changelog_creator/__init__.py
factorio_changelog_creator/cli.py
factorio_changelog_creator/creator.py
factorio_changelog_creator-1.1.2.dist-info/entry_points.txt
factorio_changelog_creator-1.1.2.dist-info/LICENSE
factorio_changelog_creator-1.1.2.dist-info/WHEEL
factorio_changelog_creator-1.1.2.dist-info/METADATA
factorio_changelog_creator-1.1.2.dist-info/RECORD
