Metadata-Version: 2.1
Name: factorio-changelog-creator
Version: 1.1.2
Summary: A script to generate multiple Factorio changelog formats.
Home-page: https://github.com/Roang-zero1/factorio-changelog-creator
License: MIT
Author: Roang_zero1
Author-email: lucas@brandstaetter.tech
Requires-Python: >=3.6,<4.0
Classifier: License :: OSI Approved :: MIT License
Classifier: Operating System :: OS Independent
Classifier: Programming Language :: Python :: 3
Classifier: Programming Language :: Python :: 3.6
Classifier: Programming Language :: Python :: 3.7
Project-URL: Documentation, https://github.com/Roang-zero1/factorio-changelog-creator
Project-URL: Repository, https://github.com/Roang-zero1/factorio-changelog-creator
